investpy/__init__.py
investpy/calculos.py
investpy/dados.py
investpy/visualizacao.py
investimentpylv-1.0.1.dist-info/METADATA
investimentpylv-1.0.1.dist-info/WHEEL
investimentpylv-1.0.1.dist-info/top_level.txt
investimentpylv-1.0.1.dist-info/RECORD
