Metadata-Version: 2.4
Name: investimentpylv
Version: 1.0.1
Summary: Uma biblioteca para análise de investimentos
Home-page: https://github.com/lvvlopes/investimentpy
Author: Vagner Lopes
Author-email: vagner.lopes@gmail.com
License: MIT
Dynamic: author
Dynamic: author-email
Dynamic: description
Dynamic: description-content-type
Dynamic: home-page
Dynamic: license
Dynamic: summary
